{"otherData": {},"traceEvents":[{"cat":"function","dur":73656,"name":"TrtSeg::setDev","ph":"X","pid":0,"tid":1684914474,"ts":1718083457868193},{"cat":"function","dur":499978,"name":"TrtSeg::loadNet","ph":"X","pid":0,"tid":1684914474,"ts":1718083457941880},{"cat":"function","dur":14,"name":"TrtSeg::createCudaStream","ph":"X","pid":0,"tid":1684914474,"ts":1718083458441878},{"cat":"function","dur":10604,"name":"TrtSeg::resMem","ph":"X","pid":0,"tid":1684914474,"ts":1718083458441896},{"cat":"function","dur":584327,"name":"TrtSeg::init","ph":"X","pid":0,"tid":1684914474,"ts":1718083457868193},{"cat":"function","dur":11663,"name":"loadSampleImage","ph":"X","pid":0,"tid":1684914474,"ts":1718083458452539},{"cat":"function","dur":1866,"name":"PreProc::norm","ph":"X","pid":0,"tid":1684914474,"ts":1718083458469092},{"cat":"function","dur":9206,"name":"PreProc::process","ph":"X","pid":0,"tid":1684914474,"ts":1718083458464225},{"cat":"function","dur":22928,"name":"PostProc::process","ph":"X","pid":0,"tid":1684914474,"ts":1718083458557285},{"cat":"function","dur":116638,"name":"TrtSeg::infer","ph":"X","pid":0,"tid":1684914474,"ts":1718083458464225},{"cat":"function","dur":37244,"name":"TrtSeg::destroy","ph":"X","pid":0,"tid":1684914474,"ts":1718083458582832},{"cat":"function","dur":751902,"name":"main","ph":"X","pid":0,"tid":1684914474,"ts":1718083457868192}]}